idesolver/__init__.py
idesolver/exceptions.py
idesolver/idesolver.py
idesolver/version.py
tests/__init__.py
tests/conftest.py
tests/test_complex_quad.py
tests/test_complex_valued.py
tests/test_misc.py
tests/test_solver_against_analytic_solutions.py
tests/test_solver_constructor_checks.py
tests/test_version.py
idesolver-1.1.0.dist-info/LICENSE
idesolver-1.1.0.dist-info/METADATA
idesolver-1.1.0.dist-info/WHEEL
idesolver-1.1.0.dist-info/top_level.txt
idesolver-1.1.0.dist-info/RECORD
